ispunct/__init__.py
ispunct/bits.py
ispunct/ispunct.py
ispunct/reinterpret.py
ispunct/unicode.py
ispunct/utils.py
ispunct-1.0.4.dist-info/licenses/LICENSE
ispunct-1.0.4.dist-info/METADATA
ispunct-1.0.4.dist-info/WHEEL
ispunct-1.0.4.dist-info/top_level.txt
ispunct-1.0.4.dist-info/RECORD
