Metadata-Version: 2.4
Name: ispunct
Version: 1.0.4
Summary: Small Python library to check if a character is a punctuation character
Author-email: "Jake W. Ireland" <jakewilliami@icloud.com>
Project-URL: Repository, https://github.com/jakewilliami/ispunct-py
Project-URL: PyPI, https://pypi.org/p/ispunct
Requires-Python: <4.0.0,>=3.9
License-File: LICENSE
Dynamic: license-file
